Metadata-Version: 2.4
Name: bjdata
Version: 0.6.6
Summary: Binary JData and UBJSON encoder/decoder
Home-page: https://github.com/NeuroJSON/pybj
Author: Qianqian Fang
Author-email: fangqq@gmail.com
Maintainer: Qianqian Fang
Maintainer-email: fangqq@gmail.com
License: Apache License 2.0
Keywords: JSON,JData,UBJSON,BJData,OpenJData,NeuroJSON,JNIfTI,Encoder,Decoder
Classifier: Development Status :: 4 - Beta
Classifier: License :: OSI Approved :: Apache Software License
Classifier: Intended Audience :: Developers
Classifier: Programming Language :: C
Classifier: Programming Language :: Python
Classifier: Programming Language :: Python :: 2.7
Classifier: Programming Language :: Python :: 3.2
Classifier: Programming Language :: Python :: 3.3
Classifier: Programming Language :: Python :: 3.4
Classifier: Programming Language :: Python :: 3.5
Classifier: Programming Language :: Python :: 3.6
Classifier: Programming Language :: Python :: 3.7
Classifier: Programming Language :: Python :: 3.8
Classifier: Programming Language :: Python :: 3.9
Classifier: Programming Language :: Python :: 3.10
Classifier: Programming Language :: Python :: 3.11
Classifier: Programming Language :: Python :: 3.12
Classifier: Programming Language :: Python :: 3.13
Classifier: Topic :: Software Development :: Libraries
Classifier: Topic :: Software Development :: Libraries :: Python Modules
License-File: LICENSE
License-File: NOTICE
Requires-Dist: numpy>=1.8.0
Provides-Extra: dev
Requires-Dist: Pympler<0.8,>=0.7; extra == "dev"
Requires-Dist: coverage<4.6,>=4.5.3; extra == "dev"
Dynamic: author
Dynamic: author-email
Dynamic: classifier
Dynamic: description
Dynamic: description-content-type
Dynamic: home-page
Dynamic: keywords
Dynamic: license
Dynamic: license-file
Dynamic: maintainer
Dynamic: maintainer-email
Dynamic: provides-extra
Dynamic: requires-dist
Dynamic: summary
